{
    "brand": [
        {
            "name": "XXX",
            "image": "logo.png",
            "price": 11
        },
        {
            "name": "Breeze Chew Mint",
            "image": "example.jpg",
            "price": 15
        },
        {
            "name": "XXX",
            "image": "logo.png",
            "price": 13
        },
        {
            "name": "XXX",
            "image": "logo.png",
            "price": 14
        },
        {
            "name": "XXX",
            "image": "logo.png",
            "price": 15
        },
        {
            "name": "XXX",
            "image": "logo.png",
            "price": 16
        },
        {
            "name": "XXX",
            "image": "logo.png",
            "price": 17
        },
        {
            "name": "XXX",
            "image": "logo.png",
            "price": 18
        },
        {
            "name": "XXX",
            "image": "logo.png",
            "price": 19
        }
    ],
    "brand2": [
        {
            "name": "XXX",
            "image": "logo.png",
            "price": 21
        },
        {
            "name": "XXX",
            "image": "logo.png",
            "price": 22
        },
        {
            "name": "XXX",
            "image": "logo.png",
            "price": 23
        }
    ],
    "brand3": [
        {
            "name": "XXX",
            "image": "logo.png",
            "price": 31
        },
        {
            "name": "XXX",
            "image": "logo.png",
            "price": 32
        },
        {
            "name": "XXX",
            "image": "logo.png",
            "price": 33
        }
    ]
}